ytad/__init__.py
ytad/_version.py
ytad/app_config.py
ytad/authentication.py
ytad/download_my_uploads.py
ytad/new_description.py
ytad/update_description.py
ytad/update_notifications.py
ytad/cli/__init__.py
ytad/cli/update_notifications.py
ytad-0.0.8.dist-info/LICENSE
ytad-0.0.8.dist-info/METADATA
ytad-0.0.8.dist-info/WHEEL
ytad-0.0.8.dist-info/entry_points.txt
ytad-0.0.8.dist-info/top_level.txt
ytad-0.0.8.dist-info/RECORD
